echocore/__init__.py
echocore/client.py
EchoCore-0.0.1.dist-info/LICENSE
EchoCore-0.0.1.dist-info/METADATA
EchoCore-0.0.1.dist-info/WHEEL
EchoCore-0.0.1.dist-info/top_level.txt
EchoCore-0.0.1.dist-info/RECORD
